setup.py
gb_distributions_test/Binomialdistribution.py
gb_distributions_test/Gaussiandistribution.py
gb_distributions_test/Generaldistribution.py
gb_distributions_test/__init__.py
gb_distributions_test.egg-info/PKG-INFO
gb_distributions_test.egg-info/SOURCES.txt
gb_distributions_test.egg-info/dependency_links.txt
gb_distributions_test.egg-info/not-zip-safe
gb_distributions_test.egg-info/top_level.txt