Metadata-Version: 1.0
Name: gb-distributions-test
Version: 0.1
Summary: Gaussian and Binomial distributions
Home-page: UNKNOWN
Author: ['test']
Author-email: UNKNOWN
License: UNKNOWN
Platform: UNKNOWN
